trabBuild-0.1.1.dist-info/DESCRIPTION.rst
trabBuild-0.1.1.dist-info/METADATA
trabBuild-0.1.1.dist-info/RECORD
trabBuild-0.1.1.dist-info/WHEEL
trabBuild-0.1.1.dist-info/entry_points.txt
trabBuild-0.1.1.dist-info/metadata.json
trabBuild-0.1.1.dist-info/top_level.txt
trabbuild/__init__.py
trabbuild/__main__.py
