Metadata-Version: 2.0
Name: trabBuild
Version: 0.1.1
Summary: A script for updating and building python dists
Home-page: UNKNOWN
Author: Scott Doucet
Author-email: duroktar@gmail.com
License: Apache Software License
Platform: UNKNOWN
Requires-Dist: pyyaml
Requires-Dist: twine
